bivium/__init__.py
bivium/alt.py
bivium/bivium.py
bivium-0.0.3.dist-info/LICENSE
bivium-0.0.3.dist-info/METADATA
bivium-0.0.3.dist-info/WHEEL
bivium-0.0.3.dist-info/top_level.txt
bivium-0.0.3.dist-info/RECORD
