Metadata-Version: 2.1
Name: bivium
Version: 0.0.3
Summary: Two-way enum-like lookups
Home-page: https://github.com/MrThearMan/bivium/
Author: Matti Lamppu
Author-email: lamppu.matti.akseli@gmail.com
License: UNKNOWN
Project-URL: Bug Tracker, https://github.com/MrThearMan/bivium/issues
Platform: UNKNOWN
Classifier: Programming Language :: Python :: 3
Classifier: License :: OSI Approved :: MIT License
Classifier: Operating System :: OS Independent
Requires-Python: >=3.8
